googlesearch/__init__.py
googlesearch/browser_agents.txt
googlesearch/googlesearch.py
google_search-1.1.1.dist-info/AUTHORS.rst
google_search-1.1.1.dist-info/LICENSE
google_search-1.1.1.dist-info/METADATA
google_search-1.1.1.dist-info/WHEEL
google_search-1.1.1.dist-info/top_level.txt
google_search-1.1.1.dist-info/RECORD
