Metadata-Version: 1.1
Name: google-search
Version: 1.1.1
Summary: Library for scraping google search results
Home-page: https://github.com/anthonyhseb/googlesearch
Author: Anthony Hseb
Author-email: anthony.hseb@hotmail.com
License: MIT license
Keywords: googlesearch
Platform: UNKNOWN
Classifier: Development Status :: 2 - Pre-Alpha
Classifier: Intended Audience :: Developers
Classifier: License :: OSI Approved :: MIT License
Classifier: Natural Language :: English
Classifier: Programming Language :: Python :: 2
Classifier: Programming Language :: Python :: 2.7
Classifier: Programming Language :: Python :: 3
Classifier: Programming Language :: Python :: 3.6
Classifier: Programming Language :: Python :: 3.8
